adicity/__init__.py
adicity/__main__.py
adicity/debugger.py
adicity/errors.py
adicity-0.6.6.dist-info/METADATA
adicity-0.6.6.dist-info/WHEEL
adicity-0.6.6.dist-info/entry_points.txt
adicity-0.6.6.dist-info/top_level.txt
adicity-0.6.6.dist-info/RECORD
